{
  "dia": [
    {
      "servico": "Saúde",
      "acessos": 458
    },
    {
      "servico": "Cartão SUS Online",
      "acessos": 423
    },
    {
      "servico": "Servidor Público",
      "acessos": 286
    },
    {
      "servico": "Documentos Pendentes",
      "acessos": 203
    },
    {
      "servico": "Cartão do Doador de Sangue",
      "acessos": 183
    },
    {
      "servico": "Trânsito",
      "acessos": 106
    },
    {
      "servico": "Portal do Servidor",
      "acessos": 95
    },
    {
      "servico": "Educação",
      "acessos": 87
    },
    {
      "servico": "Resultado de Exames Hemosul",
      "acessos": 87
    },
    {
      "servico": "Débito de Veículos",
      "acessos": 83
    },
    {
      "servico": "Carteira do Estudante - CDIEMS",
      "acessos": 67
    },
    {
      "servico": "Consultar CDIEMS",
      "acessos": 67
    },
    {
      "servico": "Documentos Assinados",
      "acessos": 66
    },
    {
      "servico": "Solicitar CDIEMS",
      "acessos": 58
    },
    {
      "servico": "Contracheque",
      "acessos": 49
    }
  ],
  "semana": [
    {
      "servico": "Saúde",
      "acessos": 6927
    },
    {
      "servico": "Cartão SUS Online",
      "acessos": 6125
    },
    {
      "servico": "Servidor Público",
      "acessos": 5887
    },
    {
      "servico": "Documentos Pendentes",
      "acessos": 3772
    },
    {
      "servico": "Educação",
      "acessos": 2901
    },
    {
      "servico": "Consultar CDIEMS",
      "acessos": 2825
    },
    {
      "servico": "Cartão do Doador de Sangue",
      "acessos": 2548
    },
    {
      "servico": "Portal do Servidor",
      "acessos": 2526
    },
    {
      "servico": "Carteira do Estudante - CDIEMS",
      "acessos": 2308
    },
    {
      "servico": "Trânsito",
      "acessos": 2177
    },
    {
      "servico": "Contracheque",
      "acessos": 1433
    },
    {
      "servico": "Débito de Veículos",
      "acessos": 1408
    },
    {
      "servico": "Resultado de Exames Hemosul",
      "acessos": 1274
    },
    {
      "servico": "Documentos Assinados",
      "acessos": 1211
    },
    {
      "servico": "Solicitar CDIEMS",
      "acessos": 1058
    }
  ],
  "mes": [
    {
      "servico": "Servidor Público",
      "acessos": 33894
    },
    {
      "servico": "Saúde",
      "acessos": 27956
    },
    {
      "servico": "Cartão SUS Online",
      "acessos": 25091
    },
    {
      "servico": "Portal do Servidor",
      "acessos": 21010
    },
    {
      "servico": "Contracheque",
      "acessos": 16320
    },
    {
      "servico": "Documentos Pendentes",
      "acessos": 15665
    },
    {
      "servico": "Cartão do Doador de Sangue",
      "acessos": 10944
    },
    {
      "servico": "Educação",
      "acessos": 9126
    },
    {
      "servico": "Consultar CDIEMS",
      "acessos": 8940
    },
    {
      "servico": "Trânsito",
      "acessos": 8210
    },
    {
      "servico": "Carteira do Estudante - CDIEMS",
      "acessos": 7347
    },
    {
      "servico": "Resultado de Exames Hemosul",
      "acessos": 5867
    },
    {
      "servico": "Documentos Assinados",
      "acessos": 5220
    },
    {
      "servico": "Débito de Veículos",
      "acessos": 4715
    },
    {
      "servico": "Solicitar CDIEMS",
      "acessos": 3311
    }
  ],
  "ano": [
    {
      "servico": "Servidor Público",
      "acessos": 354582
    },
    {
      "servico": "Saúde",
      "acessos": 331945
    },
    {
      "servico": "Cartão SUS Online",
      "acessos": 311360
    },
    {
      "servico": "Portal do Servidor",
      "acessos": 240851
    },
    {
      "servico": "Contracheque",
      "acessos": 179160
    },
    {
      "servico": "Educação",
      "acessos": 148714
    },
    {
      "servico": "Consultar CDIEMS",
      "acessos": 143922
    },
    {
      "servico": "Documentos Pendentes",
      "acessos": 140163
    },
    {
      "servico": "Cartão do Doador de Sangue",
      "acessos": 138343
    },
    {
      "servico": "Carteira do Estudante - CDIEMS",
      "acessos": 117755
    },
    {
      "servico": "Trânsito",
      "acessos": 99246
    },
    {
      "servico": "Cartão de Vacinação",
      "acessos": 68798
    },
    {
      "servico": "Solicitar CDIEMS",
      "acessos": 65551
    },
    {
      "servico": "Documentos Assinados",
      "acessos": 55136
    },
    {
      "servico": "Débito de Veículos",
      "acessos": 50704
    }
  ]
}